pyvgrid/__init__.py
pyvgrid/hybridpressurevgrid.py
pyvgrid/stdatm.py
pyvgrid/bin/mkvgrid.x
pyvgrid/cli/__init__.py
pyvgrid/cli/mkvgrid.py
pyvgrid/lib/libstdatm.so
pyvgrid-1.0.1.dist-info/LICENSE.txt
pyvgrid-1.0.1.dist-info/METADATA
pyvgrid-1.0.1.dist-info/WHEEL
pyvgrid-1.0.1.dist-info/entry_points.txt
pyvgrid-1.0.1.dist-info/top_level.txt
pyvgrid-1.0.1.dist-info/RECORD
pyvgrid.libs/libquadmath-96973f99.so.0.0.0
pyvgrid.libs/libgfortran-040039e1.so.5.0.0
