Metadata-Version: 2.2
Name: pyvgrid
Version: 1.0.1
Summary: Vertical hybrid-pressure grids
Project-URL: source, https://github.com/ACCORD-NWP/vgrid.git
Project-URL: tracker, https://github.com/ACCORD-NWP/vgrid/issues
Classifier: Development Status :: 3 - Alpha
Classifier: Intended Audience :: Science/Research
Classifier: Programming Language :: Python
Classifier: Programming Language :: Python :: 3.10
Classifier: Programming Language :: Python :: 3.11
Classifier: Programming Language :: Python :: 3.12
Classifier: Operating System :: Unix
Requires-Python: >=3.10
License-File: LICENSE.txt
Requires-Dist: bronx
Requires-Dist: ctypesForFortran<2.0.0
Provides-Extra: graphics
Requires-Dist: bokeh; extra == "graphics"
